ctunet/__init__.py
ctunet/utilities.py
ctunet/cfg/AutoImplant2020_wShapePrior.ini
ctunet/cfg/AutoImplant2020_woShapePrior.ini
ctunet/pytorch/ProblemHandler.py
ctunet/pytorch/__init__.py
ctunet/pytorch/dataset_classes.py
ctunet/pytorch/defect_generator.py
ctunet/pytorch/models.py
ctunet/pytorch/train_test.py
ctunet/pytorch/transforms.py
ctunet-0.102.dist-info/LICENSE
ctunet-0.102.dist-info/METADATA
ctunet-0.102.dist-info/WHEEL
ctunet-0.102.dist-info/entry_points.txt
ctunet-0.102.dist-info/top_level.txt
ctunet-0.102.dist-info/RECORD
